<krpano version="1.21" title="Virtual Tour">

	<include url="skin/vtourskin.xml" />
	<plugin nam="toolbox" url="plugins/toolbox/toolboxV2.js" keep="true" preload="true"/>

	<layer name="intro"
		type="container"
		keep="true"
		width="100%"
		height="100%"
		bgcolor="0x000000"
		bgalpha="0.8"
		zorder="9999"
		enabled="true"
		bgcapture="true"
		vr="true"
		onloaded="on_intro_loaded()"
		onclick="on_intro_click()">
		<layer name="intro_logo"
			url="skin/logo.png"
			align="center"
			y="-70"
			scale="0.2"
			enabled="false"
			alpha="0"
			vr="true"
		/>
		<layer name="intro_guide"
			url="skin/help_desktop.png"
			align="center" y="80"
			scale="1"
			enabled="false"
			alpha="0"
			vr="true"
		/>
	</layer>

	<hotspot name="nadirlogo" keep="true"
		url="recursos/vtourskin_nadir2.png"
		ath="0"
		atv="90"
		distorted="true"
		scale="3"
		rotate="0.0"
		alpha="0.9"
		onclick="openurl('https://refodige.intec.edu.do/');"
	/>

	<!-- onviewchange event - update logo rotation on pano rotation -->
	<events name="nadirlogo" keep="true"
		onviewchange="copy(hotspot[nadirlogo].rotate, view.hlookat);" />

	<layer name="creditos" url="recursos/creditos.png" keep="true" enabled="true" align="centercenter" x="0" y="0" visible="false" alpha="1" scale="0.6" scale.mobile="0.2" onclick="set(layer[creditos].visible,false);"/>
	<layer name="botoncreditos" url="recursos/botoncreditos.png" keep="true" enabled="true" align="leftbottom" x="10" y="5" scale="0.4" scale.mobile="0.2" onclick="set(layer[creditos].visible,true);"/>

	<action name="on_intro_loaded">
		set(hotspot[spot1].visible, false);
		set(hotspot[spot2].visible, false);
		set(hotspot[spot6].visible, false);
		set(hotspot[spot10].visible, false);
		set(hotspot[Boton-CartelBayahibe].visible, false);
		set(hotspot[nadirlogo].visible, false);
		delayedcall(2,
		tween(layer[intro_logo].alpha, 1);
		tween(layer[intro_guide].alpha, 1);
		);
	</action>

	<action name="on_intro_click">
		tween(layer[intro].alpha, 0);
		set(layer[intro].enabled, false);
		set(hotspot[Bienvenido].visible, true);
		set(hotspot[Creditos].visible, true);
		set(hotspot[Creditos].alpha, 1);
		set(hotspot[Bienvenido].alpha, 1);
		set(hotspot[nadirlogo].visible, true);
	</action>

	<!-- customize skin settings: maps, gyro, webvr, thumbnails, tooltips, layout, design, ... -->
	<skin_settings maps="true"
	               maps_type="google"
	               maps_bing_api_key=""
	               maps_google_api_key=""
	               maps_zoombuttons="false"
	               maps_loadonfirstuse="true"
	               gyro="true"
	               gyro_keeplookingdirection="false"
	               webvr="true"
	               webvr_keeplookingdirection="true"
	               webvr_prev_next_hotspots="true"
	               autotour="false"
	               littleplanetintro="true"
	               followmousecontrol="false"
	               title="true"
	               thumbs="true"
	               thumbs_width="120" thumbs_height="80" thumbs_padding="10" thumbs_crop="0|40|240|160"
	               thumbs_opened="false"
	               thumbs_text="false"
	               thumbs_dragging="true"
	               thumbs_onhoverscrolling="false"
	               thumbs_scrollbuttons="false"
	               thumbs_scrollindicator="false"
	               thumbs_loop="false"
	               tooltips_buttons="false"
	               tooltips_thumbs="false"
	               tooltips_hotspots="false"
	               tooltips_mapspots="false"
	               deeplinking="false"
	               loadscene_flags="MERGE"
	               loadscene_blend="OPENBLEND(0.5, 0.0, 0.75, 0.05, linear)"
	               loadscene_blend_prev="SLIDEBLEND(0.5, 180, 0.75, linear)"
	               loadscene_blend_next="SLIDEBLEND(0.5,   0, 0.75, linear)"
	               loadingtext=""
	               layout_width="100%"
	               layout_maxwidth="814"
	               controlbar_width="-24"
	               controlbar_height="40"
	               controlbar_offset="20"
	               controlbar_offset_closed="-40"
	               controlbar_overlap.no-fractionalscaling="10"
	               controlbar_overlap.fractionalscaling="0"
	               design_skin_images="vtourskin.png"
	               design_bgcolor="0x2D3E50"
	               design_bgalpha="0.8"
	               design_bgborder="0"
	               design_bgroundedge="1"
	               design_bgshadow="0 4 10 0x000000 0.3"
	               design_thumbborder_bgborder="3 0xFFFFFF 1.0"
	               design_thumbborder_padding="2"
	               design_thumbborder_bgroundedge="0"
	               design_text_css="color:#FFFFFF; font-family:Arial;"
	               design_text_shadow="1"
	               />

	<action name="scene3dtransition" scope="local" args="scenename, hlookatoffset">
		motionblur = 0.5;
		transitiondelay = 0.0;
		transitiontime = 0.5;
		transitiontweentype = "easeoutquad";
		
		if(caller AND caller.ishotspot,
			<!-- called from a hotspot, move toward the hotspot -->
			if(caller.depth == 0,
				<!-- 3d placed hotspot -->
				set3dtransition("image", caller.tx,caller.ty,caller.tz, motionblur, hlookatoffset, transitiondelay, transitiontime, transitiontweentype);
			  ,
				<!-- a hotspot with a spherical position -->
				caller.getcenter(h,v);
				if(v GT -50 AND v LT +50 AND caller.depth GT 120, set(v,0));
				set3dtransition("sphere", h,v,(min(caller.depth,1000)), motionblur, hlookatoffset, transitiondelay, transitiontime, transitiontweentype);
			);
		  ,
			<!-- called from a layer or a script, recenter at the new pano center (3d-model/depthmap panos only) -->
			if(image.depthmap.url,
				set3dtransition("image", 0,0,0, motionblur, hlookatoffset, transitiondelay, transitiontime, transitiontweentype);
			);
		);
		
		loadscene(get(scenename), null, MERGE, BLEND(get(transitiontime),get(transitiontweentype)));
	</action>

	<scene name="scene_Rosa_de_Bayahibe" title="Rosa_de_Bayahibe" onstart="" thumburl="panos/Rosa_de_Bayahibe.tiles/thumb.jpg" lat="18.49068333" lng="-69.95873056" alt="23.07" heading="0.0">
		
		<control bouncinglimits="calc:image.cube ? true : false" />

		<view hlookat="0.0" vlookat="0.0" fovtype="MFOV" fov="120" maxpixelzoom="2.0" fovmin="70" fovmax="140" limitview="auto" />

		<preview url="panos/Rosa_de_Bayahibe.tiles/preview.jpg" />

		<image prealign="0|0.0|0">
			<cube url="panos/Rosa_de_Bayahibe.tiles/%s/l%l/%v/l%l_%s_%v_%h.jpg" multires="512,768,1664" />
		</image>

		<hotspot name="spot6" style="green_wave" ath="-96.0712749" atv="2.2675708" linkedscene="scene_Cieba" linkedscene_lookat="-11.54007634,1.84297115,120.0" scale="0.3" zoom="true" />
		<hotspot name="spot10" style="red_wave" ath="79.8861796" atv="5.2329770" linkedscene="scene_Lengua_de_Buey" linkedscene_lookat="63.32488568,10.48618995,120.0" scale="0.3" zoom="true" />
		

		<action name="ocultar">
			tween(hotspot[Bienvenido].alpha, 0.0, 1.5);
			tween(hotspot[Creditos].alpha, 0.0, 1.5);
			set(hotspot[Creditos].enabled, false);
			set(hotspot[Bienvenido].enabled, false);
			set(hotspot[spot6].visible, true);
			set(hotspot[spot10].visible, true);
			set(hotspot[Creditos].keep, true);
			set(hotspot[Bienvenido].keep, true);
			set(hotspot[Boton-CartelBayahibe].visible, true)
		</action>

		<hotspot name="Bienvenido"
			type="image"
			url="recursos/introduccion.png"
			ath="0"
			atv="0"
			depth="2500"
			rx="0" ry="0" rz="0"
			ox="0.0" oy="0.0"
			tx="0" ty="0" tz="0"
			visible="false"
			distorted="true"
			onclick="ocultar();" />

		<hotspot name="Boton-CartelBayahibe" 
         url="Carteles/Boton-CartelBayahibe.png" 
         scale="0.8" 
         ath="-6.1752412" 
         atv="26.5636011" 
		 rx="0" ry="0" rz="0"
		 ox="0.0" oy="0.0"
		 tx="0" ty="0" tz="0"
         scale.mobile="0.2" 
		 distorted="true"
         onclick="
            set(hotspot[Boton-CartelBayahibe].enabled, false);  
            set(hotspot[CartelBayahibe].enabled, false); 

            tween(hotspot[Boton-CartelBayahibe].alpha, 0, 1);  
            tween(hotspot[CartelBayahibe].alpha, 1, 1);  

            set(hotspot[Boton-CartelBayahibe].visible, false);  
            set(hotspot[CartelBayahibe].visible, true);  

            delayedcall(1, set(hotspot[CartelBayahibe].enabled, true)); 
        "/>

		<hotspot name="CartelBayahibe" 
         url="Carteles/CartelBayahibe.png" 
         visible="false" 
         ath="-6.1752412" 
         atv="26.5636011" 
		 rx="0" ry="0" rz="0"
		 ox="0.0" oy="0.0"
		 tx="0" ty="0" tz="0"
         alpha="0"   
         scale="0.65" 
		 distorted="true"
         scale.mobile="0.2" 
         onclick="
            set(hotspot[CartelBayahibe].enabled, false); 
            tween(hotspot[CartelBayahibe].alpha, 0, 1); 
            tween(hotspot[Boton-CartelBayahibe].alpha, 1, 1);  

            delayedcall(1, set(hotspot[CartelBayahibe].visible, false));  
            delayedcall(1, set(hotspot[Boton-CartelBayahibe].visible, true)); 
            delayedcall(1, set(hotspot[Boton-CartelBayahibe].enabled, true)); 
        "/>

	</scene>

	<scene name="scene_Cieba" title="Cieba" onstart="" thumburl="panos/Cieba.tiles/thumb.jpg" lat="18.49167778" lng="-69.95795278" alt="20.25" heading="0.0">
		
		<control bouncinglimits="calc:image.cube ? true : false" />

		<view hlookat="0.0" vlookat="0.0" fovtype="MFOV" fov="120" maxpixelzoom="2.0" fovmin="70" fovmax="140" limitview="auto" />

		<preview url="panos/Cieba.tiles/preview.jpg" />

		<image prealign="0|0.0|0">
			<cube url="panos/Cieba.tiles/%s/l%l/%v/l%l_%s_%v_%h.jpg" multires="512,768,1664" />
		</image>

		<hotspot name="spot1" style="green_wave" ath="-176.0605745" atv="-0.2272191" linkedscene="scene_Cubanola" linkedscene_lookat="-5.17769050,4.24834822,120.0" scale="0.3" zoom="true" />
		<hotspot name="spot7" style="red_wave" ath="83.5138799" atv="3.0699849" linkedscene="scene_Rosa_de_Bayahibe" linkedscene_lookat="-4.13769853,10.24463254,120.0" scale="0.3" zoom="true" />

		<hotspot name="Boton-CartelCeiba" 
         url="Carteles/Boton-CartelCeiba.png" 
         scale="0.8" 
         ath="-6.1752412" 
         atv="26.5636011" 
		 rx="0" ry="0" rz="0"
		 ox="0.0" oy="0.0"
		 tx="0" ty="0" tz="0"
		 distorted="true"
         scale.mobile="0.2" 
         onclick="
            set(hotspot[Boton-CartelCeiba].enabled, false);  
            set(hotspot[CartelCeiba].enabled, false); 

            tween(hotspot[Boton-CartelCeiba].alpha, 0, 1);  
            tween(hotspot[CartelCeiba].alpha, 1, 1);  

            set(hotspot[Boton-CartelCeiba].visible, false);  
            set(hotspot[CartelCeiba].visible, true);  

            delayedcall(1, set(hotspot[CartelCeiba].enabled, true)); 
        "/>

		<hotspot name="CartelCeiba" 
         url="Carteles/CartelCeiba.png" 
         visible="false" 
         ath="-6.1752412" 
         atv="26.5636011" 
		 rx="0" ry="0" rz="0"
		 ox="0.0" oy="0.0"
		 tx="0" ty="0" tz="0"
         alpha="0"   
         scale="0.65" 
		 distorted="true"
         scale.mobile="0.2" 
         onclick="
            set(hotspot[CartelCeiba].enabled, false); 
            tween(hotspot[CartelCeiba].alpha, 0, 1); 
            tween(hotspot[Boton-CartelCeiba].alpha, 1, 1);  

            delayedcall(1, set(hotspot[CartelCeiba].visible, false));  
            delayedcall(1, set(hotspot[Boton-CartelCeiba].visible, true)); 
            delayedcall(1, set(hotspot[Boton-CartelCeiba].enabled, true)); 
        "/>

	</scene>

	<scene name="scene_Cubanola" title="Cubanola" onstart="" thumburl="panos/Cubanola.tiles/thumb.jpg" lat="18.49170833" lng="-69.95808333" alt="19.54" heading="0.0">
		
		<control bouncinglimits="calc:image.cube ? true : false" />

		<view hlookat="0.0" vlookat="0.0" fovtype="MFOV" fov="120" maxpixelzoom="2.0" fovmin="70" fovmax="140" limitview="auto" />

		<preview url="panos/Cubanola.tiles/preview.jpg" />

		<image prealign="0|0.0|0">
			<cube url="panos/Cubanola.tiles/%s/l%l/%v/l%l_%s_%v_%h.jpg" multires="512,768,1664" />
		</image>

		<hotspot name="spot2" style="green_wave" ath="-74.3084352" atv="2.8180868" linkedscene="scene_Copey" linkedscene_lookat="-4.51239536,-0.26562866,120.0" scale="0.4" zoom="true" />
		<hotspot name="spot8" style="red_wave" ath="145.7173731" atv="1.0622489" linkedscene="scene_Cieba" linkedscene_lookat="-11.54007634,1.84297115,120.0" scale="0.35" zoom="true" />

		<hotspot name="Boton-CartelCubanola" 
         url="Carteles/Boton-CartelCubanola.png" 
         scale="0.8" 
         ath="-6.1752412" 
         atv="26.5636011" 
		 rx="0" ry="0" rz="0"
		 ox="0.0" oy="0.0"
		 tx="0" ty="0" tz="0"
		 distorted="true"
         scale.mobile="0.2" 
         onclick="
            set(hotspot[Boton-CartelCubanola].enabled, false);  
            set(hotspot[CartelCubanola].enabled, false); 

            tween(hotspot[Boton-CartelCubanola].alpha, 0, 1);  
            tween(hotspot[CartelCubanola].alpha, 1, 1);  

            set(hotspot[Boton-CartelCubanola].visible, false);  
            set(hotspot[CartelCubanola].visible, true);  

            delayedcall(1, set(hotspot[CartelCubanola].enabled, true)); 
        "/>

		<hotspot name="CartelCubanola" 
         url="Carteles/CartelCubanola.png" 
         visible="false" 
         ath="-6.1752412" 
         atv="26.5636011" 
		 rx="0" ry="0" rz="0"
		 ox="0.0" oy="0.0"
		 tx="0" ty="0" tz="0"
		 distorted="true"
         alpha="0"   
         scale="0.65" 
         scale.mobile="0.2" 
         onclick="
            set(hotspot[CartelCubanola].enabled, false); 
            tween(hotspot[CartelCubanola].alpha, 0, 1); 
            tween(hotspot[Boton-CartelCubanola].alpha, 1, 1);  

            delayedcall(1, set(hotspot[CartelCubanola].visible, false));  
            delayedcall(1, set(hotspot[Boton-CartelCubanola].visible, true)); 
            delayedcall(1, set(hotspot[Boton-CartelCubanola].enabled, true)); 
        "/>

	</scene>

	<scene name="scene_Copey" title="Copey" onstart="" thumburl="panos/Copey.tiles/thumb.jpg" lat="18.49293611" lng="-69.95813056" alt="12.79" heading="0.0">
		
		<control bouncinglimits="calc:image.cube ? true : false" />

		<view hlookat="0.0" vlookat="0.0" fovtype="MFOV" fov="120" maxpixelzoom="2.0" fovmin="70" fovmax="140" limitview="auto" />

		<preview url="panos/Copey.tiles/preview.jpg" />

		<image prealign="0|0.0|0">
			<cube url="panos/Copey.tiles/%s/l%l/%v/l%l_%s_%v_%h.jpg" multires="512,768,1664" />
		</image>

		<hotspot name="spot3" style="green_wave" ath="-106.9416245" atv="10.2443056" linkedscene="scene_Lengua_de_Buey" linkedscene_lookat="63.32488568,10.48618995,120.0" scale="0.5" zoom="true" />
		<hotspot name="spot9" style="red_wave" ath="-161.3754888" atv="1.7081617" linkedscene="scene_Cubanola" linkedscene_lookat="-5.17769050,4.24834822,120.0" scale="0.3" zoom="true" />

		<hotspot name="Boton-CartelCopey" 
         url="Carteles/Boton-CartelCopey.png" 
         scale="0.8" 
		 ath="-48.1340347" 
		 atv="-0.9827969" 
		 rx="0" ry="0" rz="0"
		 ox="0.0" oy="0.0"
		 tx="0" ty="0" tz="0"
		 distorted="true"
         scale.mobile="0.2" 
         onclick="
            set(hotspot[Boton-CartelCopey].enabled, false);  
            set(hotspot[CartelCopey].enabled, false); 

            tween(hotspot[Boton-CartelCopey].alpha, 0, 1);  
            tween(hotspot[CartelCopey].alpha, 1, 1);  

            set(hotspot[Boton-CartelCopey].visible, false);  
            set(hotspot[CartelCopey].visible, true);  

            delayedcall(1, set(hotspot[CartelCopey].enabled, true)); 
        "/>

		<hotspot name="CartelCopey" 
         url="Carteles/CartelCopey.png" 
         visible="false" 
		 ath="-48.1340347" 
		 atv="-0.9827969"
		 rx="0" ry="0" rz="0"
		 ox="0.0" oy="0.0"
		 tx="0" ty="0" tz="0"
		 distorted="true"
         alpha="0"   
         scale="0.65" 
         scale.mobile="0.2" 
         onclick="
            set(hotspot[CartelCopey].enabled, false); 
            tween(hotspot[CartelCopey].alpha, 0, 1); 
            tween(hotspot[Boton-CartelCopey].alpha, 1, 1);  

            delayedcall(1, set(hotspot[CartelCopey].visible, false));  
            delayedcall(1, set(hotspot[Boton-CartelCopey].visible, true)); 
            delayedcall(1, set(hotspot[Boton-CartelCopey].enabled, true)); 
        "/>

	</scene>

	<scene name="scene_Lengua_de_Buey" title="Lengua_de_Buey" onstart="" thumburl="panos/Lengua_de_Buey.tiles/thumb.jpg" lat="18.49300000" lng="-69.95795833" alt="21.80" heading="0.0">
		
		<control bouncinglimits="calc:image.cube ? true : false" />

		<view hlookat="0.0" vlookat="0.0" fovtype="MFOV" fov="120" maxpixelzoom="2.0" fovmin="70" fovmax="140" limitview="auto" />

		<preview url="panos/Lengua_de_Buey.tiles/preview.jpg" />

		<image prealign="0|0.0|0">
			<cube url="panos/Lengua_de_Buey.tiles/%s/l%l/%v/l%l_%s_%v_%h.jpg" multires="512,768,1664" />
		</image>

		<hotspot name="spot5" style="green_wave" ath="-78.1223572" atv="1.2463638" linkedscene="scene_Rosa_de_Bayahibe" linkedscene_lookat="-4.13769853,10.24463254,120.0" scale="0.45" zoom="true" />
		<hotspot name="spot4" style="red_wave" ath="-120.3777185" atv="2.0827070" linkedscene="scene_Copey" linkedscene_lookat="-4.51239536,-0.26562866,120.0" scale="0.3" zoom="true" />
		
		<hotspot name="Boton-CartelLenguaDeBuey" 
         url="Carteles/Boton-CartelLenguaDeBuey.png" 
         scale="0.8" 
		 ath="63.0272086" 
		 atv="19.9280656"
		 rx="0" ry="0" rz="0"
		 ox="0.0" oy="0.0"
		 tx="0" ty="0" tz="0"
		 distorted="true"
         scale.mobile="0.2" 
         onclick="
            set(hotspot[Boton-CartelLenguaDeBuey].enabled, false);  
            set(hotspot[CartelLenguaDeBuey].enabled, false); 

            tween(hotspot[Boton-CartelLenguaDeBuey].alpha, 0, 1);  
            tween(hotspot[CartelLenguaDeBuey].alpha, 1, 1);  

            set(hotspot[Boton-CartelLenguaDeBuey].visible, false);  
            set(hotspot[CartelLenguaDeBuey].visible, true);  

            delayedcall(1, set(hotspot[CartelLenguaDeBuey].enabled, true)); 
        "/>

		<hotspot name="CartelLenguaDeBuey" 
         url="Carteles/CartelLenguaDeBuey.png" 
         visible="false" 
		 ath="63.0272086" 
		 atv="19.9280656"
		 rx="0" ry="0" rz="0"
		 ox="0.0" oy="0.0"
		 tx="0" ty="0" tz="0"
		 distorted="true"
         alpha="0"   
         scale="0.65" 
         scale.mobile="0.2" 
         onclick="
            set(hotspot[CartelLenguaDeBuey].enabled, false); 
            tween(hotspot[CartelLenguaDeBuey].alpha, 0, 1); 
            tween(hotspot[Boton-CartelLenguaDeBuey].alpha, 1, 1);  

            delayedcall(1, set(hotspot[CartelLenguaDeBuey].visible, false));  
            delayedcall(1, set(hotspot[Boton-CartelLenguaDeBuey].visible, true)); 
            delayedcall(1, set(hotspot[Boton-CartelLenguaDeBuey].enabled, true)); 
        "/>

	</scene>

</krpano>
